electronic_package_descriptor/__init__.py
electronic_package_descriptor/commons.py
electronic_package_descriptor/deserializer.py
electronic_package_descriptor/groups_of_pins.py
electronic_package_descriptor/packages.py
electronic_package_descriptor/parser.py
electronic_package_descriptor/pins.py
electronic_package_descriptor/serializer.py
electronic_package_descriptor_by_sporniket-0.0.7.dist-info/LICENSE
electronic_package_descriptor_by_sporniket-0.0.7.dist-info/METADATA
electronic_package_descriptor_by_sporniket-0.0.7.dist-info/WHEEL
electronic_package_descriptor_by_sporniket-0.0.7.dist-info/top_level.txt
electronic_package_descriptor_by_sporniket-0.0.7.dist-info/RECORD
